isage_pypi_publisher-0.1.8.7.dist-info/licenses/LICENSE
pypi_publisher/__init__.py
pypi_publisher/_version.py
pypi_publisher/cli.py
pypi_publisher/compiler.py
pypi_publisher/detector.py
pypi_publisher/exceptions.py
pypi_publisher/hooks.py
pypi_publisher/manylinux_builder.py
isage_pypi_publisher-0.1.8.7.dist-info/METADATA
isage_pypi_publisher-0.1.8.7.dist-info/WHEEL
isage_pypi_publisher-0.1.8.7.dist-info/entry_points.txt
isage_pypi_publisher-0.1.8.7.dist-info/top_level.txt
isage_pypi_publisher-0.1.8.7.dist-info/RECORD
