Metadata-Version: 2.4
Name: isage-pypi-publisher
Version: 0.1.8.7
Summary: Python bytecode compiler and PyPI publishing toolkit for monorepos
Author-email: IntelliStream Team <shuhao_zhang@hust.edu.cn>
Maintainer-email: IntelliStream Team <shuhao_zhang@hust.edu.cn>
License: MIT
Project-URL: Homepage, https://github.com/intellistream/pypi-publisher
Project-URL: Documentation, https://github.com/intellistream/pypi-publisher#readme
Project-URL: Repository, https://github.com/intellistream/pypi-publisher
Project-URL: Issues, https://github.com/intellistream/pypi-publisher/issues
Keywords: pypi,publishing,bytecode,compiler,monorepo,packaging,wheel,build
Classifier: Development Status :: 4 - Beta
Classifier: Environment :: Console
Classifier: Intended Audience :: Developers
Classifier: Operating System :: OS Independent
Classifier: Programming Language :: Python :: 3
Classifier: Programming Language :: Python :: 3.10
Classifier: Programming Language :: Python :: 3.11
Classifier: Programming Language :: Python :: 3.12
Classifier: Topic :: Software Development :: Build Tools
Classifier: Topic :: Software Development :: Libraries :: Python Modules
Classifier: Topic :: System :: Software Distribution
Requires-Python: >=3.10
License-File: LICENSE
Requires-Dist: rich>=13.0.0
Requires-Dist: typer>=0.9.0
Requires-Dist: build>=1.0.0
Requires-Dist: twine>=4.0.0
Requires-Dist: tomli>=2.0.0
Requires-Dist: requests>=2.28.0
Provides-Extra: dev
Requires-Dist: pytest>=7.0.0; extra == "dev"
Requires-Dist: pytest-cov>=4.0.0; extra == "dev"
Requires-Dist: ruff>=0.4.0; extra == "dev"
Requires-Dist: mypy>=1.0.0; extra == "dev"
Dynamic: license-file
